suai_observer/__init__.py
suai_observer/cli.py
suai_observer/config.py
suai_observer/report.py
suai_observer/session.py
suai_observer-0.2.1.dist-info/LICENSE
suai_observer-0.2.1.dist-info/METADATA
suai_observer-0.2.1.dist-info/WHEEL
suai_observer-0.2.1.dist-info/entry_points.txt
suai_observer-0.2.1.dist-info/top_level.txt
suai_observer-0.2.1.dist-info/RECORD
