Metadata-Version: 2.1
Name: suai-observer
Version: 0.2.1
Summary: A library and a script to get list of all reports from your SUAI profile
Author-email: lch361 <lch361@proton.me>
License: GNU GENERAL PUBLIC LICENSE
Project-URL: Homepage, https://codeberg.org/lch361/suai-observer
Keywords: web,scraping,http,html,education,login
Classifier: Programming Language :: Python :: 3
Classifier: License :: OSI Approved :: GNU General Public License v3 (GPLv3)
Classifier: Operating System :: OS Independent
Classifier: Development Status :: 4 - Beta
Classifier: Intended Audience :: Education
License-File: LICENSE
Requires-Dist: toml
Requires-Dist: beautifulsoup4
Requires-Dist: requests
